README.rst
setup.py
zappa_secrets_manager/__init__.py
zappa_secrets_manager/__version__.py
zappa_secrets_manager/get_secrets.py
zappa_secrets_manager/load_secrets.py
zappa_secrets_manager.egg-info/PKG-INFO
zappa_secrets_manager.egg-info/SOURCES.txt
zappa_secrets_manager.egg-info/dependency_links.txt
zappa_secrets_manager.egg-info/not-zip-safe
zappa_secrets_manager.egg-info/requires.txt
zappa_secrets_manager.egg-info/top_level.txt